Blauwal3_Educational-0.8.0-py3.10-nspkg.pth
orangecontrib/educational/__init__.py
orangecontrib/educational/i18n_config.py
orangecontrib/educational/locale/educational.de.yml
orangecontrib/educational/locale/educational.en.yml
orangecontrib/educational/locale/educational.zh.yml
orangecontrib/educational/tests/__init__.py
orangecontrib/educational/tutorials/__init__.py
orangecontrib/educational/widgets/__init__.py
orangecontrib/educational/widgets/owcreatetable.py
orangecontrib/educational/widgets/owgooglesheets.py
orangecontrib/educational/widgets/owgradientdescent.py
orangecontrib/educational/widgets/owkmeans.py
orangecontrib/educational/widgets/owpiecharts.py
orangecontrib/educational/widgets/owpolynomialclassification.py
orangecontrib/educational/widgets/owpolynomialregression.py
orangecontrib/educational/widgets/owrandomdata.py
orangecontrib/educational/widgets/icons/CreateTable.svg
orangecontrib/educational/widgets/icons/GoogleSheets.svg
orangecontrib/educational/widgets/icons/GradientDescent.svg
orangecontrib/educational/widgets/icons/InteractiveKMeans.svg
orangecontrib/educational/widgets/icons/PieChart.svg
orangecontrib/educational/widgets/icons/RandomData.svg
orangecontrib/educational/widgets/icons/UnivariateRegression.svg
orangecontrib/educational/widgets/icons/category.svg
orangecontrib/educational/widgets/icons/educational_category.svg
orangecontrib/educational/widgets/icons/polynomialclassification.svg
orangecontrib/educational/widgets/icons/speaker-off.svg
orangecontrib/educational/widgets/icons/speaker-on.svg
orangecontrib/educational/widgets/sounds/arrow.wav
orangecontrib/educational/widgets/sounds/clack.wav
orangecontrib/educational/widgets/tests/__init__.py
orangecontrib/educational/widgets/tests/test_owcreatetable.py
orangecontrib/educational/widgets/tests/test_owgradientdescent.py
orangecontrib/educational/widgets/tests/test_owkmeans.py
orangecontrib/educational/widgets/tests/test_owpiecharts.py
Blauwal3_Educational-0.8.0.dist-info/LICENSE
Blauwal3_Educational-0.8.0.dist-info/METADATA
Blauwal3_Educational-0.8.0.dist-info/WHEEL
Blauwal3_Educational-0.8.0.dist-info/entry_points.txt
Blauwal3_Educational-0.8.0.dist-info/namespace_packages.txt
Blauwal3_Educational-0.8.0.dist-info/top_level.txt
Blauwal3_Educational-0.8.0.dist-info/RECORD
