Metadata-Version: 2.1
Name: Blauwal3-Educational
Version: 0.8.0
Summary: 用于教学模式的蓝鲸数据挖掘附加组件。
Home-page: https://github.com/biolab/orange3-educational
Download-URL: https://github.com/biolab/orange3-educational/releases
Author: 大圣实验楼
Author-email: dashenglab@163.com
License: BSD
Keywords: orange3 add-on
License-File: LICENSE
Requires-Dist: anyqt
Requires-Dist: numpy
Requires-Dist: Blauwal3>=3.38.3
Requires-Dist: scikit-learn
Requires-Dist: scipy
Requires-Dist: pyqtgraph
Provides-Extra: doc
Requires-Dist: sphinx; extra == "doc"
Requires-Dist: recommonmark; extra == "doc"
Requires-Dist: sphinx-rtd-theme; extra == "doc"
Provides-Extra: test
Requires-Dist: coverage; extra == "test"
